[
    {
        "agent_id": 0,
        "belief": [
            0.008334185377250034,
            0.008329103556898053,
            0.008329103556898053,
            0.008329103556898053,
            0.008328786800769003
        ],
        "belief2": [
            0.011863655187136274,
            0.011861395872257924,
            0.011854163313799232,
            0.011854163313799232,
            0.01184555931284229
        ],
        "belief3": [
            0.008307139799368903,
            0.008307139799368903,
            0.008307139799368903,
            0.008307139799368903,
            0.008307139799368903
        ],
        "marginal_belief": [
            0.500101229820753,
            0.4734255690859419,
            0.5001012298207527,
            0.47342556908594197,
            0.47342556908594197,
            0.47342556908594197,
            0.5001012298207527
        ],
        "marginal_belief2": [
            0.4828447593503244,
            0.4828447593503244,
            0.5001233943533815,
            0.2923905003715882,
            0.4828447593503244,
            0.4828447593503244,
            0.5001233943533815
        ],
        "marginal_belief3": [
            0.5001012911421966,
            0.4686216034814303,
            0.5001012911421966,
            0.4686216034814303,
            0.4686216034814303,
            0.4686216034814303,
            0.5001012911421966
        ],
        "plan2_mentions": [
            [
                0,
                0,
                1,
                0,
                1,
                1,
                0
            ],
            [
                1,
                0,
                0,
                1,
                1,
                0,
                0
            ],
            [
                1,
                0,
                0,
                1,
                0,
                1,
                0
            ],
            [
                0,
                1,
                0,
                1,
                0,
                1,
                0
            ]
        ],
        "plan2_mentions_language ": null,
        "plan3_mentions": [
            [
                1,
                0,
                0,
                0,
                0,
                1,
                0
            ],
            [
                0,
                1,
                0,
                1,
                0,
                0,
                0
            ],
            [
                0,
                0,
                0,
                1,
                0,
                1,
                0
            ],
            [
                1,
                1,
                0,
                0,
                0,
                0,
                0
            ]
        ],
        "plan3_mentions_language ": null,
        "plan_mentions": [
            [
                1,
                0,
                1,
                0,
                0,
                0,
                0
            ],
            [
                0,
                1,
                0,
                0,
                0,
                0,
                1
            ],
            [
                0,
                0,
                1,
                0,
                0,
                0,
                1
            ],
            [
                0,
                1,
                0,
                0,
                0,
                1,
                0
            ]
        ],
        "plan_mentions_language ": null,
        "prior_mentions": [
            [
                0,
                0,
                1,
                0,
                0,
                0,
                1
            ],
            [
                0,
                0,
                0,
                0,
                0,
                0,
                1
            ],
            [
                0,
                0,
                1,
                0,
                0,
                0,
                1
            ],
            [
                0,
                0,
                1,
                0,
                0,
                0,
                1
            ]
        ],
        "prior_mentions_language ": null,
        "response": 0,
        "response_language": "No, I see two dark dots, that almost form a straight horizontal line",
        "response_utt": [
            0,
            0,
            0,
            1,
            1,
            0,
            0
        ],
        "utterance": [
            0,
            1,
            0,
            1,
            1,
            1,
            0
        ],
        "utterance_language": "So you see a group of 4 dots taht almost form a square?"
    },
    {
        "agent_id": 0,
        "belief": [
            0.024547111650515478,
            0.024285578575455474,
            0.024285578575455474,
            0.024285578575455474,
            0.02408186656344483
        ],
        "belief2": [
            0.01220734408928138,
            0.01220734408928138,
            0.01220734408928138,
            0.01220734408928138,
            0.012056336012474744
        ],
        "belief3": [
            0.027314534177521107,
            0.027260621881267644,
            0.027260621881267644,
            0.027260621881267644,
            0.027260621881267644
        ],
        "marginal_belief": [
            0.47175231832410774,
            0.7556701412907721,
            0.4717523183241078,
            0.4067930169433657,
            0.4067930169433657,
            0.7556701412907721,
            0.4717523183241078
        ],
        "marginal_belief2": [
            0.5207613015459368,
            0.5207613015459368,
            0.4960364416982422,
            0.27189384135775396,
            0.5207613015459367,
            0.5207613015459367,
            0.4960364416982422
        ],
        "marginal_belief3": [
            0.47301874453824905,
            0.7638689112434482,
            0.4730187445382492,
            0.37001723572583467,
            0.37001723572583467,
            0.7638689112434484,
            0.4730187445382492
        ],
        "plan2_mentions": [
            [
                0,
                1,
                1,
                0,
                1,
                0,
                0
            ],
            [
                0,
                1,
                0,
                0,
                1,
                0,
                1
            ],
            [
                0,
                1,
                1,
                0,
                0,
                1,
                0
            ],
            [
                1,
                1,
                1,
                0,
                0,
                0,
                0
            ]
        ],
        "plan2_mentions_language ": null,
        "plan3_mentions": [
            [
                1,
                0,
                0,
                0,
                0,
                1,
                0
            ],
            [
                0,
                0,
                0,
                0,
                0,
                1,
                1
            ],
            [
                1,
                1,
                0,
                0,
                0,
                0,
                0
            ],
            [
                0,
                1,
                0,
                0,
                0,
                0,
                1
            ]
        ],
        "plan3_mentions_language ": null,
        "plan_mentions": [
            [
                0,
                0,
                1,
                0,
                0,
                0,
                1
            ],
            [
                1,
                0,
                1,
                0,
                0,
                0,
                0
            ],
            [
                1,
                0,
                0,
                0,
                0,
                0,
                1
            ],
            [
                0,
                0,
                0,
                0,
                1,
                0,
                1
            ]
        ],
        "plan_mentions_language ": null,
        "prior_mentions": [
            [
                0,
                0,
                0,
                1,
                0,
                0,
                0
            ],
            [
                0,
                0,
                0,
                0,
                1,
                0,
                0
            ],
            [
                0,
                0,
                1,
                0,
                0,
                0,
                1
            ],
            [
                0,
                0,
                0,
                0,
                1,
                0,
                0
            ]
        ],
        "prior_mentions_language ": null,
        "response": 1,
        "response_language": "yes, one is lower and to the right of the other",
        "response_utt": [
            0,
            1,
            0,
            0,
            0,
            1,
            0
        ],
        "utterance": [
            0,
            1,
            0,
            0,
            0,
            1,
            0
        ],
        "utterance_language": "Hmm. Do you see two light grey large dots taht are almost exactly the same size and shade not too far apart from each other?"
    }
]