[
    {
        "agent_id": 0,
        "belief": [
            0.02131212748762501,
            0.021072204263056876,
            0.021072204263056876,
            0.021072204263056876,
            0.021072204263056876
        ],
        "belief2": [
            0.008463387135058153,
            0.008463387135058153,
            0.008463387135058153,
            0.008463387135058153,
            0.00834594311258802
        ],
        "belief3": [
            0.013708935145851036,
            0.013708935145851036,
            0.013708935145851036,
            0.013673534409515721,
            0.013673534409515721
        ],
        "marginal_belief": [
            0.7872007273461962,
            0.4752500252550763,
            0.4752500252550763,
            0.4752500252550763,
            0.4752500252550763,
            0.7872007273461963,
            0.4752500252550763
        ],
        "marginal_belief2": [
            0.5247448374080227,
            0.5247448374080227,
            0.4967560724740881,
            0.4967560724740881,
            0.5247448374080227,
            0.5247448374080227,
            0.4967560724740881
        ],
        "marginal_belief3": [
            0.6839422259983008,
            0.6839422259983008,
            0.586767204757859,
            0.48959218351741723,
            0.48959218351741723,
            0.5867672047578589,
            0.48959218351741723
        ],
        "plan2_mentions": [
            [
                0,
                0,
                1,
                0,
                1,
                1,
                0
            ],
            [
                1,
                0,
                0,
                1,
                1,
                0,
                0
            ],
            [
                1,
                0,
                0,
                1,
                0,
                1,
                0
            ],
            [
                0,
                1,
                0,
                1,
                0,
                1,
                0
            ]
        ],
        "plan2_mentions_language ": null,
        "plan3_mentions": [
            [
                1,
                0,
                0,
                0,
                0,
                1,
                0
            ],
            [
                0,
                1,
                1,
                0,
                0,
                0,
                0
            ],
            [
                1,
                1,
                0,
                0,
                0,
                0,
                0
            ],
            [
                0,
                1,
                0,
                0,
                1,
                0,
                0
            ]
        ],
        "plan3_mentions_language ": null,
        "plan_mentions": [
            [
                1,
                0,
                1,
                0,
                0,
                0,
                0
            ],
            [
                0,
                1,
                0,
                0,
                0,
                0,
                1
            ],
            [
                0,
                0,
                1,
                0,
                0,
                0,
                1
            ],
            [
                0,
                1,
                0,
                0,
                0,
                1,
                0
            ]
        ],
        "plan_mentions_language ": null,
        "prior_mentions": [
            [
                0,
                0,
                1,
                0,
                1,
                0,
                0
            ],
            [
                1,
                0,
                0,
                0,
                0,
                1,
                0
            ],
            [
                0,
                0,
                1,
                0,
                1,
                1,
                0
            ],
            [
                0,
                0,
                1,
                0,
                1,
                0,
                0
            ]
        ],
        "prior_mentions_language ": null,
        "response": 1,
        "response_language": "yes I see them, which one do you want me to choose?",
        "response_utt": [
            1,
            0,
            0,
            0,
            0,
            1,
            0
        ],
        "utterance": [
            1,
            0,
            0,
            0,
            0,
            1,
            0
        ],
        "utterance_language": "i have 2 small dots, one is darker, the other one is lighter and under the dark one"
    }
]