[
    {
        "agent_id": 0,
        "belief": [
            0.04362161512158105,
            0.04355501848650505,
            0.04355501848650505,
            0.04355501848650505,
            0.04355501848650505
        ],
        "belief2": [
            0.03157615300616955,
            0.03157615300616955,
            0.03152794604425411,
            0.03152794604425411,
            0.03152794604425411
        ],
        "belief3": [
            0.044157955124936255,
            0.04414839367669556,
            0.04414839367669556,
            0.04414839367669556,
            0.04414839367669556
        ],
        "marginal_belief": [
            0.4905732585921946,
            0.8720466481168142,
            0.49057325859219464,
            0.8720466481168141,
            0.49057325859219464,
            0.872046648116814,
            0.49057325859219464
        ],
        "marginal_belief2": [
            0.4933338013697655,
            0.6312438985284363,
            0.49333380136976557,
            0.8798509367211576,
            0.6312438985284361,
            0.8798509367211576,
            0.4933338013697655
        ],
        "marginal_belief3": [
            0.49290540540540523,
            0.8270780214176443,
            0.492905405405405,
            0.8270780214176442,
            0.492905405405405,
            0.8270780214176441,
            0.492905405405405
        ],
        "plan2_mentions": null,
        "plan2_mentions_language": null,
        "plan2_partner_ref": null,
        "plan2_plan": null,
        "plan3_mentions": null,
        "plan3_mentions_language": null,
        "plan3_partner_ref": null,
        "plan3_plan": null,
        "plan_mentions": null,
        "plan_mentions_language": null,
        "plan_partner_ref": null,
        "plan_plan": null,
        "prior_mentions": null,
        "prior_mentions_language": null,
        "prior_partner_ref": null,
        "prior_plan": null,
        "response": null,
        "response_language": "I have a cluster of 3 dots that make a triangleish figure two dark one lighter grey all big",
        "response_utt": [
            0,
            1,
            0,
            1,
            0,
            1,
            0
        ],
        "utterance": null,
        "utterance_language": null
    },
    {
        "agent_id": 1,
        "belief": [
            0.0078125,
            0.0078125,
            0.0078125,
            0.0078125,
            0.0078125
        ],
        "belief2": [
            0.0078125,
            0.0078125,
            0.0078125,
            0.0078125,
            0.0078125
        ],
        "belief3": [
            0.0078125,
            0.0078125,
            0.0078125,
            0.0078125,
            0.0078125
        ],
        "marginal_belief": [
            0.5,
            0.5,
            0.5,
            0.5,
            0.5,
            0.5,
            0.5
        ],
        "marginal_belief2": [
            0.5,
            0.5,
            0.5,
            0.5,
            0.5,
            0.5,
            0.5
        ],
        "marginal_belief3": [
            0.5,
            0.5,
            0.5,
            0.5,
            0.5,
            0.5,
            0.5
        ],
        "plan2_mentions": [
            [
                1,
                0,
                1,
                0,
                0,
                0,
                1
            ],
            [
                0,
                0,
                1,
                1,
                0,
                0,
                1
            ],
            [
                0,
                0,
                1,
                0,
                0,
                1,
                1
            ],
            [
                1,
                0,
                0,
                1,
                0,
                0,
                0
            ]
        ],
        "plan2_mentions_language": null,
        "plan2_partner_ref": null,
        "plan2_plan": null,
        "plan3_mentions": [
            [
                1,
                1,
                0,
                1,
                0,
                0,
                0
            ],
            [
                0,
                1,
                0,
                1,
                1,
                0,
                0
            ],
            [
                0,
                1,
                0,
                0,
                1,
                1,
                0
            ],
            [
                0,
                0,
                0,
                1,
                1,
                1,
                0
            ]
        ],
        "plan3_mentions_language": "i have a triangle of dots , the one on the right is a darker one and a medium black one to the right of the large one <eos>",
        "plan3_partner_ref": [
            [
                [
                    0,
                    1,
                    1,
                    0,
                    1,
                    0,
                    0
                ]
            ],
            [
                [
                    0,
                    1,
                    0,
                    0,
                    0,
                    0,
                    0
                ]
            ],
            [
                [
                    0,
                    0,
                    0,
                    0,
                    1,
                    0,
                    0
                ]
            ],
            [
                [
                    0,
                    0,
                    1,
                    0,
                    0,
                    0,
                    0
                ]
            ]
        ],
        "plan3_plan": [
            [
                [
                    1,
                    1,
                    0,
                    1,
                    0,
                    0,
                    0
                ],
                [
                    1,
                    0,
                    0,
                    0,
                    0,
                    0,
                    0
                ],
                [
                    0,
                    1,
                    0,
                    0,
                    0,
                    0,
                    0
                ],
                [
                    0,
                    0,
                    0,
                    1,
                    0,
                    0,
                    0
                ]
            ]
        ],
        "plan_mentions": [
            [
                0,
                0,
                0,
                0,
                0,
                1,
                1
            ],
            [
                0,
                0,
                0,
                0,
                1,
                1,
                0
            ],
            [
                0,
                0,
                1,
                0,
                0,
                1,
                0
            ],
            [
                0,
                0,
                0,
                1,
                0,
                0,
                1
            ]
        ],
        "plan_mentions_language": null,
        "plan_partner_ref": null,
        "plan_plan": null,
        "prior_mentions": [
            [
                0,
                1,
                0,
                1,
                0,
                1,
                0
            ],
            [
                0,
                1,
                0,
                0,
                0,
                0,
                0
            ],
            [
                0,
                1,
                0,
                1,
                0,
                1,
                0
            ],
            [
                0,
                1,
                0,
                1,
                0,
                1,
                0
            ]
        ],
        "prior_mentions_language": "i have that . let 's pick the black dot <selection>",
        "prior_partner_ref": [
            [
                [
                    0,
                    1,
                    1,
                    0,
                    1,
                    0,
                    0
                ]
            ],
            [
                [
                    0,
                    1,
                    0,
                    0,
                    0,
                    0,
                    0
                ]
            ]
        ],
        "prior_plan": [
            [
                [
                    0,
                    1,
                    0,
                    1,
                    0,
                    1,
                    0
                ],
                [
                    0,
                    1,
                    0,
                    0,
                    0,
                    0,
                    0
                ]
            ]
        ],
        "response": null,
        "response_language": "I only have one dark gray circle almost black.",
        "response_utt": [
            0,
            1,
            0,
            0,
            0,
            0,
            0
        ],
        "utterance": [
            0,
            1,
            0,
            1,
            0,
            1,
            0
        ],
        "utterance_language": "I only have one dark gray circle almost black."
    },
    {
        "agent_id": 0,
        "belief": [
            0.13026823269262164,
            0.12989207822132073,
            0.12989207822132073,
            0.12989207822132073,
            0.019847314628560906
        ],
        "belief2": [
            0.04171465960833505,
            0.04171465960833505,
            0.04171465960833505,
            0.04171465960833505,
            0.041453998721187435
        ],
        "belief3": [
            0.13933079954963778,
            0.13924032500447567,
            0.13924032500447567,
            0.13924032500447567,
            0.017647631256088477
        ],
        "marginal_belief": [
            0.4732675967401285,
            0.8678242619403955,
            0.4732675967401284,
            0.8678242619403956,
            0.8282980911094294,
            0.8678242619403956,
            0.8282980911094295
        ],
        "marginal_belief2": [
            0.49079207583486867,
            0.6551560472585098,
            0.625391427851225,
            0.8859108881881949,
            0.6551560472585096,
            0.8859108881881949,
            0.6253914278512249
        ],
        "marginal_belief3": [
            0.47674915886303315,
            0.80985985596813,
            0.47674915886303326,
            0.80985985596813,
            0.8367407310327576,
            0.8098598559681299,
            0.8367407310327576
        ],
        "plan2_mentions": [
            [
                0,
                1,
                0,
                1,
                1,
                0,
                1
            ],
            [
                0,
                1,
                0,
                1,
                0,
                0,
                1
            ],
            [
                0,
                1,
                0,
                0,
                1,
                0,
                1
            ],
            [
                0,
                1,
                0,
                1,
                1,
                0,
                0
            ]
        ],
        "plan2_mentions_language": null,
        "plan2_partner_ref": null,
        "plan2_plan": null,
        "plan3_mentions": [
            [
                0,
                1,
                0,
                0,
                1,
                0,
                0
            ],
            [
                0,
                1,
                0,
                0,
                0,
                0,
                1
            ],
            [
                1,
                0,
                0,
                0,
                1,
                0,
                0
            ],
            [
                0,
                0,
                0,
                0,
                1,
                0,
                1
            ]
        ],
        "plan3_mentions_language": "i have two black dots . one is smaller than the other . <eos>",
        "plan3_partner_ref": [
            [
                [
                    0,
                    1,
                    0,
                    0,
                    0,
                    1,
                    0
                ]
            ],
            [
                [
                    0,
                    1,
                    0,
                    0,
                    0,
                    0,
                    0
                ]
            ],
            [
                [
                    0,
                    0,
                    0,
                    0,
                    0,
                    1,
                    0
                ]
            ]
        ],
        "plan3_plan": [
            [
                [
                    0,
                    1,
                    0,
                    0,
                    1,
                    0,
                    0
                ],
                [
                    0,
                    1,
                    0,
                    0,
                    0,
                    0,
                    0
                ],
                [
                    0,
                    0,
                    0,
                    0,
                    1,
                    0,
                    0
                ]
            ]
        ],
        "plan_mentions": [
            [
                1,
                0,
                1,
                0,
                0,
                0,
                0
            ],
            [
                0,
                1,
                0,
                0,
                0,
                0,
                1
            ],
            [
                0,
                0,
                1,
                0,
                0,
                0,
                1
            ],
            [
                0,
                1,
                0,
                0,
                0,
                1,
                0
            ]
        ],
        "plan_mentions_language": null,
        "plan_partner_ref": null,
        "plan_plan": null,
        "prior_mentions": [
            [
                0,
                1,
                0,
                0,
                0,
                0,
                0
            ],
            [
                0,
                1,
                0,
                0,
                1,
                0,
                0
            ],
            [
                0,
                1,
                1,
                0,
                0,
                0,
                0
            ],
            [
                0,
                1,
                1,
                0,
                0,
                0,
                0
            ]
        ],
        "prior_mentions_language": "is there a small black dot above and to the left of the large light grey dot ? <eos>",
        "prior_partner_ref": [
            [
                [
                    0,
                    1,
                    0,
                    0,
                    0,
                    0,
                    0
                ]
            ],
            [
                [
                    0,
                    0,
                    0,
                    1,
                    0,
                    0,
                    0
                ]
            ]
        ],
        "prior_plan": [
            [
                [
                    0,
                    1,
                    0,
                    0,
                    0,
                    0,
                    0
                ],
                [
                    0,
                    0,
                    1,
                    0,
                    0,
                    0,
                    0
                ]
            ]
        ],
        "response": null,
        "response_language": "Do you have a small grey dot with a darker one and almost black one around it",
        "response_utt": [
            0,
            0,
            0,
            0,
            1,
            0,
            1
        ],
        "utterance": [
            0,
            1,
            0,
            0,
            0,
            0,
            0
        ],
        "utterance_language": "Do you have a small grey dot with a darker one and almost black one around it"
    },
    {
        "agent_id": 1,
        "belief": [
            0.051944361852047996,
            0.04558293908903618,
            0.04558293908903618,
            0.04558293908903618,
            0.04558293908903618
        ],
        "belief2": [
            0.06057989753997743,
            0.05222550090137698,
            0.05222550090137698,
            0.05222550090137698,
            0.05222550090137698
        ],
        "belief3": [
            0.05961905460951261,
            0.05220056925686696,
            0.05220056925686696,
            0.05220056925686696,
            0.05220056925686696
        ],
        "marginal_belief": [
            0.5234127451894572,
            0.10818157347018843,
            0.8201612633645743,
            0.5234127451894572,
            0.8201612633645742,
            0.5234127451894574,
            0.5234127451894574
        ],
        "marginal_belief2": [
            0.5324203432948542,
            0.19093058111340525,
            0.8361154043102422,
            0.19093058111340527,
            0.6309802445291914,
            0.5324203432948543,
            0.6309802445291914
        ],
        "marginal_belief3": [
            0.5254728175768254,
            0.05469514582110007,
            0.8383122920336664,
            0.525472817576825,
            0.8383122920336662,
            0.525472817576825,
            0.525472817576825
        ],
        "plan2_mentions": [
            [
                1,
                0,
                0,
                1,
                0,
                0,
                0
            ],
            [
                1,
                0,
                0,
                0,
                0,
                1,
                0
            ],
            [
                1,
                0,
                1,
                0,
                0,
                0,
                0
            ],
            [
                1,
                0,
                0,
                0,
                0,
                0,
                1
            ]
        ],
        "plan2_mentions_language": null,
        "plan2_partner_ref": null,
        "plan2_plan": null,
        "plan3_mentions": [
            [
                0,
                1,
                0,
                1,
                1,
                1,
                1
            ],
            [
                0,
                0,
                0,
                1,
                1,
                1,
                1
            ],
            [
                0,
                1,
                0,
                0,
                1,
                1,
                1
            ],
            [
                0,
                1,
                0,
                1,
                1,
                0,
                1
            ]
        ],
        "plan3_mentions_language": "i have a cluster of 5 dots . a dark one to the right and a medium grey dot below and to the right of the large dark gray dot . there is a larger dark gray dot above and to the left of the small one <eos>",
        "plan3_partner_ref": [
            [
                [
                    1,
                    1,
                    1,
                    0,
                    1,
                    0,
                    0
                ]
            ],
            [
                [
                    0,
                    1,
                    0,
                    0,
                    0,
                    0,
                    0
                ]
            ],
            [
                [
                    0,
                    0,
                    0,
                    0,
                    0,
                    1,
                    0
                ]
            ],
            [
                [
                    0,
                    0,
                    0,
                    0,
                    0,
                    0,
                    1
                ]
            ],
            [
                [
                    0,
                    0,
                    0,
                    0,
                    0,
                    0,
                    1
                ]
            ],
            [
                [
                    0,
                    0,
                    0,
                    0,
                    0,
                    1,
                    0
                ]
            ]
        ],
        "plan3_plan": [
            [
                [
                    0,
                    1,
                    0,
                    1,
                    1,
                    1,
                    1
                ],
                [
                    0,
                    1,
                    0,
                    0,
                    0,
                    0,
                    0
                ],
                [
                    0,
                    0,
                    0,
                    1,
                    0,
                    0,
                    0
                ],
                [
                    0,
                    0,
                    0,
                    0,
                    1,
                    0,
                    0
                ],
                [
                    0,
                    0,
                    0,
                    0,
                    0,
                    1,
                    0
                ],
                [
                    0,
                    0,
                    0,
                    0,
                    0,
                    0,
                    1
                ]
            ]
        ],
        "plan_mentions": [
            [
                0,
                0,
                1,
                0,
                1,
                0,
                0
            ],
            [
                1,
                0,
                0,
                0,
                1,
                0,
                0
            ],
            [
                1,
                0,
                0,
                0,
                0,
                0,
                1
            ],
            [
                0,
                0,
                1,
                0,
                0,
                0,
                1
            ]
        ],
        "plan_mentions_language": null,
        "plan_partner_ref": null,
        "plan_plan": null,
        "prior_mentions": [
            [
                0,
                1,
                0,
                1,
                0,
                1,
                0
            ],
            [
                0,
                1,
                0,
                1,
                0,
                1,
                0
            ],
            [
                0,
                1,
                0,
                1,
                0,
                1,
                0
            ],
            [
                0,
                1,
                0,
                1,
                0,
                1,
                0
            ]
        ],
        "prior_mentions_language": "i have a triangle of dots , the one on the left is black and the one on the right is large and lighter , the one on the left is a large grey dot . the one on the right is a bit larger and lighter than the one on the right . <eos>",
        "prior_partner_ref": [
            [
                [
                    0,
                    1,
                    1,
                    0,
                    1,
                    0,
                    0
                ]
            ],
            [
                [
                    0,
                    0,
                    0,
                    0,
                    1,
                    0,
                    0
                ]
            ],
            [
                [
                    0,
                    0,
                    1,
                    0,
                    0,
                    0,
                    0
                ]
            ],
            [
                [
                    0,
                    0,
                    0,
                    0,
                    1,
                    0,
                    0
                ]
            ],
            [
                [
                    0,
                    0,
                    1,
                    0,
                    0,
                    0,
                    0
                ]
            ],
            [
                [
                    0,
                    0,
                    0,
                    0,
                    1,
                    0,
                    0
                ]
            ]
        ],
        "prior_plan": [
            [
                [
                    0,
                    1,
                    0,
                    1,
                    0,
                    1,
                    0
                ],
                [
                    0,
                    1,
                    0,
                    0,
                    0,
                    0,
                    0
                ],
                [
                    0,
                    0,
                    0,
                    1,
                    0,
                    0,
                    0
                ],
                [
                    0,
                    0,
                    0,
                    0,
                    0,
                    1,
                    0
                ],
                [
                    0,
                    0,
                    0,
                    1,
                    0,
                    0,
                    0
                ],
                [
                    0,
                    0,
                    0,
                    0,
                    0,
                    1,
                    0
                ]
            ]
        ],
        "response": 0,
        "response_language": "no i do not have those dots together. I have a kinda triangle with a larger lighter circle near my top left. there is a medium and dark gry with it all large",
        "response_utt": [
            0,
            1,
            1,
            0,
            1,
            0,
            0
        ],
        "utterance": [
            0,
            1,
            0,
            1,
            0,
            1,
            0
        ],
        "utterance_language": "no i do not have those dots together. I have a kinda triangle with a larger lighter circle near my top left. there is a medium and dark gry with it all large"
    },
    {
        "agent_id": 0,
        "belief": [
            0.1821143512712667,
            0.18158848916273262,
            0.18158848916273262,
            0.18158848916273262,
            0.02776059750790974
        ],
        "belief2": [
            0.05158566537029708,
            0.05158566537029708,
            0.05158566537029708,
            0.05158566537029708,
            0.05123719628152716
        ],
        "belief3": [
            0.19820793331024783,
            0.19807922686004634,
            0.19807922686004634,
            0.19807922686004634,
            0.025112255735571607
        ],
        "marginal_belief": [
            0.4833804401008496,
            0.9850569395654731,
            0.48338044010084946,
            0.9850569395654731,
            0.852841311964667,
            0.9850569395654731,
            0.852841311964667
        ],
        "marginal_belief2": [
            0.49529864937839624,
            0.6640517511215129,
            0.6313308105854105,
            0.986343674376503,
            0.6640517511215126,
            0.986343674376503,
            0.6313308105854105
        ],
        "marginal_belief3": [
            0.4847131481799809,
            0.9837367938917342,
            0.4847131481799809,
            0.9837367938917342,
            0.865478322956693,
            0.9837367938917342,
            0.865478322956693
        ],
        "plan2_mentions": [
            [
                0,
                1,
                0,
                1,
                1,
                0,
                0
            ],
            [
                0,
                1,
                0,
                1,
                0,
                0,
                1
            ],
            [
                0,
                1,
                1,
                1,
                0,
                0,
                0
            ],
            [
                0,
                1,
                0,
                1,
                0,
                0,
                0
            ]
        ],
        "plan2_mentions_language": null,
        "plan2_partner_ref": null,
        "plan2_plan": null,
        "plan3_mentions": [
            [
                0,
                0,
                1,
                1,
                1,
                0,
                0
            ],
            [
                0,
                0,
                1,
                0,
                1,
                0,
                1
            ],
            [
                0,
                0,
                1,
                0,
                1,
                1,
                0
            ],
            [
                1,
                0,
                1,
                0,
                1,
                0,
                0
            ]
        ],
        "plan3_mentions_language": "i have a triangle of three dots . the top one is large and light gray , the one on the right is smaller , the one on the left is slightly larger <eos>",
        "plan3_partner_ref": [
            [
                [
                    0,
                    1,
                    0,
                    1,
                    0,
                    1,
                    0
                ]
            ],
            [
                [
                    0,
                    0,
                    0,
                    1,
                    0,
                    0,
                    0
                ]
            ],
            [
                [
                    0,
                    0,
                    0,
                    0,
                    0,
                    0,
                    1
                ]
            ],
            [
                [
                    0,
                    0,
                    0,
                    0,
                    1,
                    0,
                    0
                ]
            ]
        ],
        "plan3_plan": [
            [
                [
                    0,
                    0,
                    1,
                    1,
                    1,
                    0,
                    0
                ],
                [
                    0,
                    0,
                    1,
                    0,
                    0,
                    0,
                    0
                ],
                [
                    0,
                    0,
                    0,
                    1,
                    0,
                    0,
                    0
                ],
                [
                    0,
                    0,
                    0,
                    0,
                    1,
                    0,
                    0
                ]
            ]
        ],
        "plan_mentions": [
            [
                0,
                0,
                1,
                1,
                1,
                0,
                0
            ],
            [
                1,
                0,
                1,
                0,
                1,
                0,
                0
            ],
            [
                0,
                0,
                1,
                0,
                1,
                0,
                1
            ],
            [
                0,
                0,
                1,
                0,
                1,
                1,
                0
            ]
        ],
        "plan_mentions_language": null,
        "plan_partner_ref": null,
        "plan_plan": null,
        "prior_mentions": [
            [
                0,
                1,
                1,
                0,
                1,
                0,
                0
            ],
            [
                0,
                1,
                1,
                0,
                1,
                0,
                0
            ],
            [
                0,
                1,
                1,
                0,
                1,
                0,
                0
            ],
            [
                0,
                1,
                1,
                0,
                1,
                0,
                0
            ]
        ],
        "prior_mentions_language": "i have that too . let 's pick the large light grey dot <selection>",
        "prior_partner_ref": [
            [
                [
                    0,
                    1,
                    0,
                    1,
                    0,
                    1,
                    0
                ]
            ],
            [
                [
                    0,
                    0,
                    0,
                    1,
                    0,
                    0,
                    0
                ]
            ]
        ],
        "prior_plan": [
            [
                [
                    0,
                    1,
                    1,
                    0,
                    1,
                    0,
                    0
                ],
                [
                    0,
                    0,
                    1,
                    0,
                    0,
                    0,
                    0
                ]
            ]
        ],
        "response": 1,
        "response_language": "Okay I think I have that triangle also you want to choose the lighter one?",
        "response_utt": [
            0,
            1,
            0,
            1,
            0,
            1,
            0
        ],
        "utterance": [
            0,
            1,
            1,
            0,
            1,
            0,
            0
        ],
        "utterance_language": "Okay I think I have that triangle also you want to choose the lighter one?"
    },
    {
        "agent_id": 1,
        "belief": [
            0.04018879839405136,
            0.035723376350267885,
            0.035723376350267885,
            0.035723376350267885,
            0.035723376350267885
        ],
        "belief2": [
            0.0281107825874332,
            0.024987362299940623,
            0.024987362299940623,
            0.024987362299940623,
            0.024987362299940623
        ],
        "belief3": [
            0.035834248148883696,
            0.03185266502122996,
            0.03185266502122996,
            0.03185266502122996,
            0.03185266502122996
        ],
        "marginal_belief": [
            0.5267065423286382,
            0.5181202713595975,
            0.9672645477400188,
            0.5267065423286381,
            0.9672645477400189,
            0.5267065423286381,
            0.5267065423286381
        ],
        "marginal_belief2": [
            0.5317577971042187,
            0.5258268479949773,
            0.974352252660144,
            0.5258268479949774,
            0.673613021003046,
            0.5317577971042187,
            0.673613021003046
        ],
        "marginal_belief3": [
            0.519145289110389,
            0.4526040514078945,
            0.8932897060065651,
            0.5191452891103892,
            0.8932897060065652,
            0.5191452891103892,
            0.5191452891103892
        ],
        "plan2_mentions": [
            [
                1,
                0,
                0,
                0,
                0,
                0,
                1
            ],
            [
                1,
                0,
                1,
                0,
                0,
                0,
                0
            ],
            [
                1,
                0,
                0,
                0,
                0,
                1,
                0
            ],
            [
                1,
                0,
                0,
                1,
                0,
                0,
                0
            ]
        ],
        "plan2_mentions_language": null,
        "plan2_partner_ref": null,
        "plan2_plan": null,
        "plan3_mentions": [
            [
                1,
                1,
                0,
                1,
                0,
                1,
                0
            ],
            [
                0,
                1,
                1,
                1,
                0,
                1,
                0
            ],
            [
                1,
                1,
                0,
                1,
                0,
                0,
                0
            ],
            [
                1,
                1,
                0,
                0,
                0,
                1,
                0
            ]
        ],
        "plan3_mentions_language": "yes , i have that . the one on the left is the darkest , the left one is black and the bottom one is medium gray and the top is black ? <eos>",
        "plan3_partner_ref": [
            [
                [
                    0,
                    1,
                    1,
                    0,
                    1,
                    0,
                    0
                ]
            ],
            [
                [
                    0,
                    0,
                    0,
                    0,
                    1,
                    0,
                    0
                ]
            ],
            [
                [
                    0,
                    1,
                    0,
                    0,
                    0,
                    0,
                    0
                ]
            ],
            [
                [
                    0,
                    0,
                    1,
                    0,
                    0,
                    0,
                    0
                ]
            ],
            [
                [
                    0,
                    1,
                    0,
                    0,
                    0,
                    0,
                    0
                ]
            ]
        ],
        "plan3_plan": [
            [
                [
                    1,
                    1,
                    0,
                    1,
                    0,
                    1,
                    0
                ],
                [
                    1,
                    0,
                    0,
                    0,
                    0,
                    0,
                    0
                ],
                [
                    0,
                    1,
                    0,
                    0,
                    0,
                    0,
                    0
                ],
                [
                    0,
                    0,
                    0,
                    1,
                    0,
                    0,
                    0
                ],
                [
                    0,
                    0,
                    0,
                    0,
                    0,
                    1,
                    0
                ]
            ]
        ],
        "plan_mentions": [
            [
                1,
                0,
                0,
                0,
                0,
                0,
                1
            ],
            [
                0,
                0,
                1,
                0,
                1,
                0,
                0
            ],
            [
                1,
                0,
                0,
                0,
                1,
                0,
                0
            ],
            [
                0,
                0,
                1,
                0,
                0,
                0,
                1
            ]
        ],
        "plan_mentions_language": null,
        "plan_partner_ref": null,
        "plan_plan": null,
        "prior_mentions": null,
        "prior_mentions_language": "yes <selection>",
        "prior_partner_ref": null,
        "prior_plan": [
            []
        ],
        "response": 1,
        "response_language": "Yes we can",
        "response_utt": null,
        "utterance": null,
        "utterance_language": "Yes we can"
    }
]