[
    {
        "agent_id": 0,
        "belief": [
            0.02131212748762501,
            0.021072204263056876,
            0.021072204263056876,
            0.021072204263056876,
            0.021072204263056876
        ],
        "configs": [
            [
                0,
                0,
                1,
                0,
                0,
                1,
                0
            ],
            [
                0,
                1,
                1,
                0,
                0,
                1,
                0
            ],
            [
                0,
                0,
                1,
                0,
                1,
                1,
                0
            ],
            [
                0,
                0,
                1,
                0,
                0,
                1,
                1
            ],
            [
                0,
                0,
                1,
                1,
                0,
                1,
                0
            ]
        ],
        "marginal_belief": [
            0.47525002525507637,
            0.47525002525507637,
            0.7872007273461962,
            0.47525002525507637,
            0.47525002525507637,
            0.7872007273461964,
            0.4752500252550764
        ],
        "plan_mentions": [
            [
                1,
                0,
                1,
                0,
                0,
                0,
                0
            ],
            [
                0,
                1,
                0,
                0,
                0,
                0,
                1
            ],
            [
                0,
                0,
                1,
                0,
                0,
                0,
                1
            ],
            [
                0,
                1,
                0,
                0,
                0,
                1,
                0
            ]
        ],
        "plan_mentions_language ": null,
        "prior_mentions": [
            [
                0,
                0,
                1,
                0,
                0,
                0,
                0
            ],
            [
                0,
                0,
                0,
                0,
                0,
                1,
                0
            ],
            [
                0,
                1,
                0,
                1,
                1,
                1,
                1
            ],
            [
                0,
                1,
                0,
                1,
                1,
                0,
                1
            ]
        ],
        "prior_mentions_language ": null,
        "response": 1,
        "response_language": "yes .",
        "response_utt": null,
        "utterance": [
            0,
            0,
            1,
            0,
            0,
            1,
            0
        ],
        "utterance_language": "do you see two black dots close together ?"
    },
    {
        "agent_id": 0,
        "belief": [
            0.0123543866677141,
            0.012109968091973209,
            0.012109968091973209,
            0.010196701086038252,
            0.010196701086038252
        ],
        "configs": [
            [
                0,
                0,
                0,
                0,
                0,
                0,
                0
            ],
            [
                0,
                0,
                0,
                0,
                0,
                1,
                0
            ],
            [
                0,
                0,
                1,
                0,
                0,
                0,
                0
            ],
            [
                0,
                1,
                0,
                0,
                0,
                1,
                0
            ],
            [
                0,
                0,
                1,
                0,
                0,
                0,
                1
            ]
        ],
        "marginal_belief": [
            0.45968931097818416,
            0.45968931097818416,
            0.5529278779438976,
            0.4596893109781841,
            0.4596893109781841,
            0.5529278779438975,
            0.45968931097818405
        ],
        "plan_mentions": [
            [
                0,
                1,
                1,
                0,
                0,
                1,
                0
            ],
            [
                1,
                0,
                1,
                0,
                0,
                1,
                0
            ],
            [
                0,
                0,
                1,
                0,
                1,
                1,
                0
            ],
            [
                0,
                0,
                1,
                0,
                0,
                1,
                1
            ]
        ],
        "plan_mentions_language ": null,
        "prior_mentions": [
            [
                0,
                0,
                1,
                0,
                0,
                0,
                0
            ],
            [
                0,
                0,
                0,
                0,
                0,
                1,
                0
            ],
            [
                0,
                0,
                1,
                0,
                0,
                1,
                0
            ],
            [
                0,
                0,
                1,
                0,
                0,
                1,
                0
            ]
        ],
        "prior_mentions_language ": null,
        "response": 0,
        "response_language": "no .",
        "response_utt": null,
        "utterance": [
            0,
            0,
            1,
            0,
            0,
            1,
            0
        ],
        "utterance_language": "is one below and to the right of the other ?"
    },
    {
        "agent_id": 0,
        "belief": [
            0.012639331147826215,
            0.012392423566183529,
            0.012392423566183529,
            0.010434579909994319,
            0.010434579909994319
        ],
        "configs": [
            [
                0,
                0,
                0,
                0,
                0,
                0,
                0
            ],
            [
                0,
                0,
                0,
                0,
                0,
                1,
                0
            ],
            [
                0,
                0,
                1,
                0,
                0,
                0,
                0
            ],
            [
                1,
                0,
                0,
                0,
                0,
                1,
                0
            ],
            [
                1,
                0,
                1,
                0,
                0,
                0,
                0
            ]
        ],
        "marginal_belief": [
            0.4496737921506051,
            0.4496737921506051,
            0.550302200965712,
            0.4496737921506051,
            0.4496737921506051,
            0.550302200965712,
            0.44967379215060505
        ],
        "plan_mentions": [
            [
                0,
                0,
                1,
                0,
                0,
                1,
                0
            ],
            [
                0,
                0,
                1,
                1,
                0,
                0,
                0
            ],
            [
                1,
                0,
                1,
                0,
                0,
                0,
                0
            ],
            [
                0,
                1,
                1,
                0,
                0,
                0,
                0
            ]
        ],
        "plan_mentions_language ": null,
        "prior_mentions": [
            [
                0,
                0,
                1,
                0,
                0,
                0,
                0
            ],
            [
                0,
                0,
                0,
                0,
                0,
                1,
                0
            ],
            [
                0,
                0,
                1,
                0,
                0,
                1,
                0
            ],
            [
                1,
                0,
                0,
                0,
                0,
                0,
                0
            ]
        ],
        "prior_mentions_language ": null,
        "response": 0,
        "response_language": "no .",
        "response_utt": null,
        "utterance": [
            1,
            1,
            0,
            1,
            1,
            0,
            1
        ],
        "utterance_language": "do you see a cluster of five grey dots ?"
    },
    {
        "agent_id": 0,
        "belief": [
            0.013091238217145014,
            0.01287483920196413,
            0.01287483920196413,
            0.010857340998137064,
            0.010857340998137064
        ],
        "configs": [
            [
                0,
                0,
                0,
                0,
                0,
                0,
                0
            ],
            [
                0,
                0,
                0,
                0,
                0,
                1,
                0
            ],
            [
                0,
                0,
                1,
                0,
                0,
                0,
                0
            ],
            [
                1,
                0,
                0,
                0,
                0,
                1,
                0
            ],
            [
                1,
                0,
                1,
                0,
                0,
                0,
                0
            ]
        ],
        "marginal_belief": [
            0.453516019160691,
            0.4329661018623012,
            0.5471245638965548,
            0.4329661018623012,
            0.4329661018623012,
            0.5471245638965547,
            0.43296610186230117
        ],
        "plan_mentions": [
            [
                0,
                0,
                1,
                0,
                0,
                1,
                0
            ],
            [
                0,
                0,
                0,
                1,
                0,
                1,
                0
            ],
            [
                0,
                0,
                1,
                0,
                0,
                0,
                1
            ],
            [
                0,
                0,
                1,
                1,
                0,
                0,
                0
            ]
        ],
        "plan_mentions_language ": null,
        "prior_mentions": [
            [
                0,
                0,
                0,
                0,
                0,
                1,
                0
            ],
            [
                1,
                1,
                0,
                1,
                1,
                0,
                1
            ],
            [
                1,
                1,
                0,
                1,
                1,
                0,
                1
            ],
            [
                0,
                0,
                1,
                0,
                0,
                0,
                0
            ]
        ],
        "prior_mentions_language ": null,
        "response": 0,
        "response_language": "no .",
        "response_utt": null,
        "utterance": [
            0,
            1,
            0,
            1,
            1,
            0,
            1
        ],
        "utterance_language": "do you see a cluster of four grey dots ?"
    },
    {
        "agent_id": 0,
        "belief": [
            0.0822973633644862,
            0.07820434496269354,
            0.05855197675587418,
            0.05855197675587418,
            0.04623463749249146
        ],
        "configs": [
            [
                0,
                0,
                1,
                1,
                1,
                1,
                1
            ],
            [
                1,
                0,
                1,
                1,
                1,
                1,
                1
            ],
            [
                0,
                0,
                1,
                1,
                1,
                0,
                1
            ],
            [
                0,
                0,
                0,
                1,
                1,
                1,
                1
            ],
            [
                1,
                0,
                1,
                1,
                1,
                0,
                1
            ]
        ],
        "marginal_belief": [
            0.4148077923630532,
            0.2873635659378511,
            0.5756221239595881,
            0.7911490792952125,
            0.7911490792952125,
            0.5756221239595882,
            0.7911490792952125
        ],
        "plan_mentions": [
            [
                0,
                0,
                1,
                0,
                0,
                1,
                0
            ],
            [
                1,
                0,
                1,
                0,
                0,
                0,
                0
            ],
            [
                1,
                0,
                0,
                0,
                0,
                1,
                0
            ],
            [
                0,
                0,
                1,
                0,
                0,
                0,
                1
            ]
        ],
        "plan_mentions_language ": null,
        "prior_mentions": [
            [
                0,
                0,
                0,
                0,
                0,
                1,
                0
            ],
            [
                0,
                0,
                1,
                0,
                0,
                0,
                0
            ],
            [
                0,
                0,
                0,
                1,
                0,
                0,
                1
            ],
            [
                1,
                1,
                0,
                1,
                1,
                0,
                1
            ]
        ],
        "prior_mentions_language ": null,
        "response": 1,
        "response_language": "yes .",
        "response_utt": null,
        "utterance": [
            0,
            0,
            0,
            1,
            1,
            0,
            1
        ],
        "utterance_language": "do you see a triangle of three grey dots ?"
    },
    {
        "agent_id": 0,
        "belief": [
            0.21779181908768305,
            0.20696005137554196,
            0.1549520058420791,
            0.12235538773888123,
            0.07677010211201471
        ],
        "configs": [
            [
                0,
                0,
                1,
                1,
                1,
                1,
                1
            ],
            [
                1,
                0,
                1,
                1,
                1,
                1,
                1
            ],
            [
                0,
                0,
                1,
                1,
                1,
                0,
                1
            ],
            [
                1,
                0,
                1,
                1,
                1,
                0,
                1
            ],
            [
                0,
                1,
                1,
                1,
                1,
                1,
                1
            ]
        ],
        "marginal_belief": [
            0.4332723070590966,
            0.21232517879442886,
            0.9347388213845368,
            0.9776760863102651,
            0.9776760863102651,
            0.609475826025272,
            0.9776760863102651
        ],
        "plan_mentions": [
            [
                0,
                0,
                1,
                0,
                1,
                0,
                1
            ],
            [
                0,
                0,
                0,
                1,
                1,
                1,
                0
            ],
            [
                0,
                0,
                0,
                1,
                0,
                1,
                1
            ],
            [
                0,
                0,
                1,
                1,
                1,
                0,
                0
            ]
        ],
        "plan_mentions_language ": null,
        "prior_mentions": [
            [
                0,
                0,
                0,
                0,
                0,
                0,
                1
            ],
            [
                0,
                1,
                0,
                0,
                0,
                0,
                0
            ],
            [
                0,
                0,
                0,
                0,
                1,
                0,
                0
            ],
            [
                0,
                1,
                0,
                0,
                1,
                0,
                1
            ]
        ],
        "prior_mentions_language ": null,
        "response": 1,
        "response_language": "yes .",
        "response_utt": null,
        "utterance": [
            0,
            0,
            1,
            1,
            1,
            0,
            1
        ],
        "utterance_language": "is there a big black dot below and to the left of it ?"
    }
]