[
    {
        "agent_id": 0,
        "belief": [
            0.021312127487625013,
            0.02107220426305688,
            0.02107220426305688,
            0.02107220426305688,
            0.02107220426305688
        ],
        "belief2": [
            0.013835377250221334,
            0.013835377250221334,
            0.013835377250221334,
            0.013835377250221334,
            0.01367962422533364
        ],
        "belief3": [
            0.022662102059925096,
            0.02260358146067416,
            0.02260358146067416,
            0.02260358146067416,
            0.02260358146067416
        ],
        "marginal_belief": [
            0.47525002525507637,
            0.7872007273461963,
            0.4752500252550765,
            0.4752500252550765,
            0.4752500252550765,
            0.7872007273461965,
            0.4752500252550765
        ],
        "marginal_belief2": [
            0.48724464701446074,
            0.8281306358002433,
            0.5110338721841498,
            0.5110338721841498,
            0.48724464701446085,
            0.5110338721841498,
            0.5110338721841498
        ],
        "marginal_belief3": [
            0.4775280898876405,
            0.8040730337078659,
            0.47752808988764056,
            0.47752808988764056,
            0.47752808988764056,
            0.8040730337078659,
            0.47752808988764056
        ],
        "plan2_mentions": null,
        "plan2_mentions_language": null,
        "plan2_partner_ref": null,
        "plan2_plan": null,
        "plan3_mentions": null,
        "plan3_mentions_language": null,
        "plan3_partner_ref": null,
        "plan3_plan": null,
        "plan_mentions": null,
        "plan_mentions_language": null,
        "plan_partner_ref": null,
        "plan_plan": null,
        "prior_mentions": null,
        "prior_mentions_language": null,
        "prior_partner_ref": null,
        "prior_plan": null,
        "response": null,
        "response_language": "tiny black dot with larger slightly lighter dot up to its left?",
        "response_utt": [
            0,
            1,
            0,
            0,
            0,
            1,
            0
        ],
        "utterance": null,
        "utterance_language": null
    },
    {
        "agent_id": 1,
        "belief": [
            0.021312127487625013,
            0.02107220426305688,
            0.02107220426305688,
            0.02107220426305688,
            0.02107220426305688
        ],
        "belief2": [
            0.012198250939577913,
            0.012198250939577913,
            0.012198250939577913,
            0.012198250939577913,
            0.012060928013876844
        ],
        "belief3": [
            0.022662102059925096,
            0.02260358146067416,
            0.02260358146067416,
            0.02260358146067416,
            0.02260358146067416
        ],
        "marginal_belief": [
            0.47525002525507637,
            0.7872007273461963,
            0.4752500252550765,
            0.4752500252550765,
            0.4752500252550765,
            0.4752500252550765,
            0.7872007273461965
        ],
        "marginal_belief2": [
            0.4895345475570974,
            0.6118820468343451,
            0.6118820468343451,
            0.611882046834345,
            0.48953454755709735,
            0.48953454755709735,
            0.611882046834345
        ],
        "marginal_belief3": [
            0.4775280898876405,
            0.8040730337078659,
            0.47752808988764056,
            0.47752808988764056,
            0.47752808988764056,
            0.47752808988764056,
            0.8040730337078659
        ],
        "plan2_mentions": [
            [
                0,
                1,
                1,
                0,
                1,
                0,
                0
            ],
            [
                0,
                1,
                0,
                1,
                1,
                0,
                0
            ],
            [
                0,
                1,
                0,
                0,
                1,
                1,
                0
            ],
            [
                0,
                1,
                0,
                0,
                1,
                0,
                1
            ]
        ],
        "plan2_mentions_language": null,
        "plan2_partner_ref": null,
        "plan2_plan": null,
        "plan3_mentions": [
            [
                1,
                1,
                0,
                0,
                0,
                1,
                0
            ],
            [
                0,
                1,
                0,
                0,
                0,
                1,
                1
            ],
            [
                0,
                1,
                0,
                0,
                1,
                1,
                0
            ],
            [
                0,
                1,
                0,
                1,
                0,
                1,
                0
            ]
        ],
        "plan3_mentions_language": "i see a cluster of three dots . the top one is large and light grey , the one on the right is a little bigger and darker , the one on the right is smaller and very dark <eos>",
        "plan3_partner_ref": [
            [
                [
                    0,
                    1,
                    1,
                    0,
                    0,
                    0,
                    1
                ]
            ],
            [
                [
                    0,
                    0,
                    0,
                    0,
                    0,
                    0,
                    0
                ]
            ],
            [
                [
                    0,
                    1,
                    0,
                    0,
                    0,
                    0,
                    0
                ]
            ],
            [
                [
                    0,
                    0,
                    0,
                    0,
                    0,
                    0,
                    1
                ]
            ]
        ],
        "plan3_plan": [
            [
                [
                    1,
                    1,
                    0,
                    0,
                    0,
                    1,
                    0
                ],
                [
                    1,
                    0,
                    0,
                    0,
                    0,
                    0,
                    0
                ],
                [
                    0,
                    1,
                    0,
                    0,
                    0,
                    0,
                    0
                ],
                [
                    0,
                    0,
                    0,
                    0,
                    0,
                    1,
                    0
                ]
            ]
        ],
        "plan_mentions": [
            [
                1,
                1,
                0,
                0,
                0,
                1,
                0
            ],
            [
                0,
                1,
                0,
                0,
                0,
                1,
                1
            ],
            [
                0,
                1,
                0,
                1,
                0,
                1,
                0
            ],
            [
                0,
                1,
                1,
                0,
                0,
                1,
                0
            ]
        ],
        "plan_mentions_language": null,
        "plan_partner_ref": null,
        "plan_plan": null,
        "prior_mentions": [
            [
                0,
                0,
                0,
                0,
                0,
                1,
                0
            ],
            [
                0,
                1,
                0,
                0,
                0,
                1,
                0
            ],
            [
                0,
                1,
                0,
                0,
                0,
                0,
                0
            ],
            [
                0,
                0,
                0,
                0,
                0,
                0,
                1
            ]
        ],
        "prior_mentions_language": "yes i have that , choose the small black one ? <eos>",
        "prior_partner_ref": [
            [
                [
                    1,
                    0,
                    0,
                    0,
                    0,
                    1,
                    0
                ]
            ],
            [
                [
                    0,
                    0,
                    0,
                    0,
                    0,
                    0,
                    1
                ]
            ]
        ],
        "prior_plan": [
            [
                [
                    0,
                    1,
                    0,
                    0,
                    0,
                    1,
                    0
                ],
                [
                    0,
                    0,
                    0,
                    0,
                    0,
                    1,
                    0
                ]
            ]
        ],
        "response": null,
        "response_language": "I see a medium black dot with a tiny black dot down and to the right",
        "response_utt": [
            0,
            1,
            0,
            0,
            0,
            0,
            1
        ],
        "utterance": [
            0,
            0,
            0,
            0,
            0,
            1,
            0
        ],
        "utterance_language": "I see a medium black dot with a tiny black dot down and to the right"
    },
    {
        "agent_id": 0,
        "belief": [
            0.02408227959412707,
            0.023534297045946413,
            0.023534297045946413,
            0.023534297045946413,
            0.023534297045946413
        ],
        "belief2": [
            0.014260600258514616,
            0.014260600258514616,
            0.014260600258514616,
            0.014260600258514616,
            0.013936106057801479
        ],
        "belief3": [
            0.024084039005994505,
            0.023885358758751116,
            0.023885358758751116,
            0.023885358758751116,
            0.023885358758751116
        ],
        "marginal_belief": [
            0.47163780705439506,
            0.800225248991722,
            0.47163780705439506,
            0.47163780705439506,
            0.47163780705439506,
            0.8657505390645066,
            0.47163780705439506
        ],
        "marginal_belief2": [
            0.4839575922849618,
            0.8277953906742175,
            0.5126641899881985,
            0.5126641899881985,
            0.4839575922849621,
            0.5126641899881985,
            0.5126641899881985
        ],
        "marginal_belief3": [
            0.47574281146772834,
            0.8187696913415347,
            0.47574281146772845,
            0.47574281146772845,
            0.47574281146772845,
            0.8430926060205154,
            0.5000657261467093
        ],
        "plan2_mentions": [
            [
                0,
                1,
                1,
                0,
                0,
                1,
                0
            ],
            [
                1,
                1,
                1,
                0,
                0,
                0,
                0
            ],
            [
                1,
                0,
                0,
                1,
                0,
                0,
                1
            ],
            [
                0,
                0,
                0,
                1,
                1,
                0,
                1
            ]
        ],
        "plan2_mentions_language": null,
        "plan2_partner_ref": null,
        "plan2_plan": null,
        "plan3_mentions": [
            [
                0,
                1,
                0,
                1,
                0,
                0,
                1
            ],
            [
                0,
                1,
                1,
                0,
                0,
                0,
                1
            ],
            [
                0,
                1,
                0,
                0,
                1,
                0,
                1
            ],
            [
                1,
                1,
                0,
                0,
                0,
                0,
                1
            ]
        ],
        "plan3_mentions_language": "i have a cluster of 3 small dots , one is large and the other is medium grey . the bottom one is a little darker . <eos>",
        "plan3_partner_ref": [
            [
                [
                    0,
                    0,
                    1,
                    0,
                    0,
                    0,
                    1
                ]
            ],
            [
                [
                    1,
                    0,
                    0,
                    0,
                    0,
                    0,
                    0
                ]
            ],
            [
                [
                    0,
                    0,
                    1,
                    0,
                    0,
                    0,
                    0
                ]
            ],
            [
                [
                    0,
                    0,
                    0,
                    0,
                    0,
                    0,
                    1
                ]
            ]
        ],
        "plan3_plan": [
            [
                [
                    0,
                    1,
                    0,
                    1,
                    0,
                    0,
                    1
                ],
                [
                    0,
                    1,
                    0,
                    0,
                    0,
                    0,
                    0
                ],
                [
                    0,
                    0,
                    0,
                    1,
                    0,
                    0,
                    0
                ],
                [
                    0,
                    0,
                    0,
                    0,
                    0,
                    0,
                    1
                ]
            ]
        ],
        "plan_mentions": [
            [
                1,
                1,
                0,
                0,
                0,
                0,
                1
            ],
            [
                0,
                1,
                0,
                0,
                0,
                1,
                1
            ],
            [
                0,
                1,
                0,
                1,
                0,
                0,
                1
            ],
            [
                0,
                1,
                0,
                0,
                1,
                0,
                1
            ]
        ],
        "plan_mentions_language": null,
        "plan_partner_ref": null,
        "plan_plan": null,
        "prior_mentions": [
            [
                0,
                1,
                0,
                0,
                0,
                0,
                1
            ],
            [
                0,
                1,
                0,
                0,
                0,
                0,
                1
            ],
            [
                0,
                0,
                0,
                0,
                0,
                0,
                1
            ],
            [
                0,
                1,
                0,
                0,
                0,
                0,
                0
            ]
        ],
        "prior_mentions_language": "i see that . click the larger black dot <selection>",
        "prior_partner_ref": [
            [
                [
                    0,
                    1,
                    0,
                    0,
                    0,
                    1,
                    0
                ]
            ],
            [
                [
                    0,
                    1,
                    0,
                    0,
                    0,
                    0,
                    0
                ]
            ]
        ],
        "prior_plan": [
            [
                [
                    0,
                    1,
                    0,
                    0,
                    0,
                    0,
                    1
                ],
                [
                    0,
                    1,
                    0,
                    0,
                    0,
                    0,
                    0
                ]
            ]
        ],
        "response": 1,
        "response_language": "yes! click that tiny black dot!",
        "response_utt": [
            0,
            0,
            0,
            0,
            0,
            1,
            0
        ],
        "utterance": [
            0,
            1,
            0,
            0,
            0,
            0,
            1
        ],
        "utterance_language": "yes! click that tiny black dot!"
    }
]